clovers_sarof/modules/game_collection/__init__.py
clovers_sarof/modules/game_collection/action.py
clovers_sarof/modules/game_collection/collection/__init__.py
clovers_sarof/modules/game_collection/collection/blackjack.py
clovers_sarof/modules/game_collection/collection/bohemia_dice.py
clovers_sarof/modules/game_collection/collection/buckshot_roulette.py
clovers_sarof/modules/game_collection/collection/cantrell.py
clovers_sarof/modules/game_collection/collection/dice.py
clovers_sarof/modules/game_collection/collection/fortress/core.py
clovers_sarof/modules/game_collection/collection/horse_race/__init__.py
clovers_sarof/modules/game_collection/collection/horse_race/config.py
clovers_sarof/modules/game_collection/collection/horse_race/core/__init__.py
clovers_sarof/modules/game_collection/collection/horse_race/core/event_library/Stand.json
clovers_sarof/modules/game_collection/collection/horse_race/core/event_library/“日常，真的很日常”.json
clovers_sarof/modules/game_collection/collection/horse_race/core/event_library/克苏鲁.json
clovers_sarof/modules/game_collection/collection/horse_race/core/event_library/基础事件.json
clovers_sarof/modules/game_collection/collection/horse_race/core/event_library/复刻经典事件集合v1.json
clovers_sarof/modules/game_collection/collection/horse_race/core/event_library/崩坏集合v1.json
clovers_sarof/modules/game_collection/collection/horse_race/core/event_library/群友日常.json
clovers_sarof/modules/game_collection/collection/horse_race/core/event_library/芜湖事件合集.json
clovers_sarof/modules/game_collection/collection/horse_race/core/event_library/赫尔事件集v1.json
clovers_sarof/modules/game_collection/collection/horse_race/core/event_library/赫尔的赛马场事件簿.json
clovers_sarof/modules/game_collection/collection/horse_race/core/horse.py
clovers_sarof/modules/game_collection/collection/horse_race/core/start.py
clovers_sarof/modules/game_collection/collection/poker_battle.py
clovers_sarof/modules/game_collection/collection/russian_roulette.py
clovers_sarof_game_collection-0.1.0.dist-info/METADATA
clovers_sarof_game_collection-0.1.0.dist-info/WHEEL
clovers_sarof_game_collection-0.1.0.dist-info/RECORD
