Metadata-Version: 2.3
Name: clovers-sarof-game-collection
Version: 0.1.0
Summary: 
Author: KarisAya
Author-email: karisaya@foxmail.com
Requires-Python: >=3.12,<4.0
Classifier: Programming Language :: Python :: 3
Classifier: Programming Language :: Python :: 3.12
Classifier: Programming Language :: Python :: 3.13
Requires-Dist: clovers-sarof (>=0.1.0,<1.0.0)
Requires-Dist: pydantic (>=2.10.6,<3.0.0)
